personal_finance_tracker/__init__.py
personal_finance_tracker/main.py
personal_finance_tracker/test.py
personal_finance_tracker-0.1.0.dist-info/METADATA
personal_finance_tracker-0.1.0.dist-info/WHEEL
personal_finance_tracker-0.1.0.dist-info/entry_points.txt
personal_finance_tracker-0.1.0.dist-info/licenses/LICENSE.md
personal_finance_tracker-0.1.0.dist-info/RECORD
