Metadata-Version: 2.4
Name: personal-finance-tracker
Version: 0.1.0
Summary: A Model Context Protocol (MCP) server for tracking personal finances: expenses, income, and budget summaries.
Author-email: Lantip <lantip@gmail.com>
License: ABRMS
License-File: LICENSE.md
Keywords: budget,finance,llm,mcp,personal
Classifier: Development Status :: 4 - Beta
Classifier: Intended Audience :: Developers
Classifier: License :: OSI Approved :: MIT License
Classifier: Programming Language :: Python :: 3
Classifier: Programming Language :: Python :: 3.10
Requires-Python: >=3.10
Requires-Dist: mcp>=1.4.1
